MANIFEST.in
README.rst
setup.py
docs/HISTORY.txt
ftw/__init__.py
ftw.keywordwidget.egg-info/PKG-INFO
ftw.keywordwidget.egg-info/SOURCES.txt
ftw.keywordwidget.egg-info/dependency_links.txt
ftw.keywordwidget.egg-info/entry_points.txt
ftw.keywordwidget.egg-info/namespace_packages.txt
ftw.keywordwidget.egg-info/not-zip-safe
ftw.keywordwidget.egg-info/requires.txt
ftw.keywordwidget.egg-info/top_level.txt
ftw/keywordwidget/__init__.py
ftw/keywordwidget/behavior.py
ftw/keywordwidget/compat.py
ftw/keywordwidget/configure.zcml
ftw/keywordwidget/field.py
ftw/keywordwidget/lawgiver.zcml
ftw/keywordwidget/permission.zcml
ftw/keywordwidget/search.py
ftw/keywordwidget/testing.py
ftw/keywordwidget/utils.py
ftw/keywordwidget/vocabularies.py
ftw/keywordwidget/widget.py
ftw/keywordwidget/widget.zcml
ftw/keywordwidget/Extensions/__init__.py
ftw/keywordwidget/Extensions/install.py
ftw/keywordwidget/locales/ftw.keywordwidget.pot
ftw/keywordwidget/locales/de/LC_MESSAGES/ftw.keywordwidget.po
ftw/keywordwidget/locales/fr/LC_MESSAGES/ftw.keywordwidget.po
ftw/keywordwidget/profiles/default/jsregistry.xml
ftw/keywordwidget/profiles/default/metadata.xml
ftw/keywordwidget/profiles/default/rolemap.xml
ftw/keywordwidget/profiles/default_plone5/metadata.xml
ftw/keywordwidget/profiles/default_plone5/registry.xml
ftw/keywordwidget/profiles/default_plone5/rolemap.xml
ftw/keywordwidget/profiles/select2js/cssregistry.xml
ftw/keywordwidget/profiles/select2js/jsregistry.xml
ftw/keywordwidget/profiles/select2js/metadata.xml
ftw/keywordwidget/profiles/uninstall/.gitkeep
ftw/keywordwidget/profiles/uninstall/jsregistry.xml
ftw/keywordwidget/profiles/uninstall/rolemap.xml
ftw/keywordwidget/profiles/uninstall_plone5/registry.xml
ftw/keywordwidget/profiles/uninstall_plone5/rolemap.xml
ftw/keywordwidget/resources/bundle/ftw-keywordwidget-compiled.css
ftw/keywordwidget/resources/bundle/ftw-keywordwidget-compiled.js
ftw/keywordwidget/resources/css/main.css
ftw/keywordwidget/resources/css/select2.plone.css
ftw/keywordwidget/resources/js/keywordwidget.js
ftw/keywordwidget/resources/js/keywordwidget_5.x.js
ftw/keywordwidget/resources/js/keywordwidget_javascript-compiled.js
ftw/keywordwidget/resources/js/main.js
ftw/keywordwidget/resources/scss/ftwkeywordwidget.scss
ftw/keywordwidget/resources/select2/dist/css/select2.css
