Metadata-Version: 2.1
Name: ftw.keywordwidget
Version: 2.2.4
Summary: A z3c form keyword widget using select2.
Home-page: https://github.com/4teamwork/ftw.keywordwidget
Author: 4teamwork AG
Author-email: mailto:info@4teamwork.ch
Maintainer: 4teamwork
License: GPL2
Keywords: ftw keyword widget
Platform: UNKNOWN
Classifier: Framework :: Plone
Classifier: Framework :: Plone :: 4.3
Classifier: Framework :: Plone :: 5.1
Classifier: License :: OSI Approved :: GNU General Public License (GPL)
Classifier: Programming Language :: Python
Classifier: Programming Language :: Python :: 2.7
Classifier: Topic :: Software Development :: Libraries :: Python Modules
Provides-Extra: tests
